lxpyodbc.cpython-38-x86_64-linux-gnu.so
lxpyodbc.pyi
lxpyodbc-2.7.202509241259.dist-info/LICENSE.txt
lxpyodbc-2.7.202509241259.dist-info/METADATA
lxpyodbc-2.7.202509241259.dist-info/WHEEL
lxpyodbc-2.7.202509241259.dist-info/top_level.txt
lxpyodbc-2.7.202509241259.dist-info/RECORD
