Metadata-Version: 2.1
Name: lxpyodbc
Version: 2.7.202509241259
Summary: DB API module for ODBC (LX fork)
Home-page: https://gitlab.leanxcale.com
Author-email: Michael Kleehammer <michael@kleehammer.com>, leanXcale <support@leanxcale.com>
Maintainer: LX Support
Maintainer-email: leanXcale <support@leanxcale.com>
License: MIT-0 License
Project-URL: Homepage, http://leanxcale.com
Classifier: License :: OSI Approved :: MIT No Attribution License (MIT-0)
Classifier: Operating System :: Microsoft :: Windows
Classifier: Operating System :: POSIX
Classifier: Programming Language :: Python
Classifier: Programming Language :: Python :: 3
Classifier: Topic :: Database
Requires-Python: >=3.8
License-File: LICENSE.txt
